examplemul/__init__.py
examplemul/multiplication.py
examplemul-0.1.2.dist-info/LICENSE
examplemul-0.1.2.dist-info/METADATA
examplemul-0.1.2.dist-info/WHEEL
examplemul-0.1.2.dist-info/top_level.txt
examplemul-0.1.2.dist-info/RECORD
