Metadata-Version: 2.1
Name: examplemul
Version: 0.1.2
Summary: A simple example library to perform multiplication
Home-page: https://github.com/nandhinikesavan20/hello_world
Author: Nandhini
Author-email: nandhini67288@gmail.com
Classifier: Programming Language :: Python :: 3
Classifier: License :: OSI Approved :: MIT License
Classifier: Operating System :: OS Independent
Requires-Python: >=3.10
License-File: LICENSE
